{
  "generatedAt": "2025-12-12T08:18:13.412Z",
  "totalEntries": 967,
  "successCount": 967,
  "errorCount": 0,
  "chunkSize": 100,
  "chunkFiles": [
    "n4-details-chunk-0.json",
    "n4-details-chunk-1.json",
    "n4-details-chunk-2.json",
    "n4-details-chunk-3.json",
    "n4-details-chunk-4.json",
    "n4-details-chunk-5.json",
    "n4-details-chunk-6.json",
    "n4-details-chunk-7.json",
    "n4-details-chunk-8.json",
    "n4-details-chunk-9.json"
  ],
  "entryToChunk": {
    "-かげつ": "n4-details-chunk-0.json",
    "あいさつ": "n4-details-chunk-0.json",
    "あいだ": "n4-details-chunk-0.json",
    "あかちゃん": "n4-details-chunk-0.json",
    "あご": "n4-details-chunk-0.json",
    "あしおと": "n4-details-chunk-0.json",
    "あじ": "n4-details-chunk-0.json",
    "あす": "n4-details-chunk-0.json",
    "あせ": "n4-details-chunk-0.json",
    "あそび": "n4-details-chunk-0.json",
    "あつさ": "n4-details-chunk-0.json",
    "あめ": "n4-details-chunk-0.json",
    "あんしん": "n4-details-chunk-0.json",
    "あんぜん": "n4-details-chunk-0.json",
    "あんない": "n4-details-chunk-0.json",
    "いか": "n4-details-chunk-0.json",
    "いがい": "n4-details-chunk-0.json",
    "いがく": "n4-details-chunk-0.json",
    "いきかた": "n4-details-chunk-0.json",
    "いけん": "n4-details-chunk-0.json",
    "いし": "n4-details-chunk-0.json",
    "いじょう": "n4-details-chunk-0.json",
    "いちど": "n4-details-chunk-0.json",
    "いちにちじゅう": "n4-details-chunk-0.json",
    "いっしょ": "n4-details-chunk-0.json",
    "いっしょうけんめい": "n4-details-chunk-0.json",
    "いと": "n4-details-chunk-0.json",
    "いない": "n4-details-chunk-0.json",
    "いなか": "n4-details-chunk-0.json",
    "いのち": "n4-details-chunk-0.json",
    "いま": "n4-details-chunk-0.json",
    "いろがみ": "n4-details-chunk-0.json",
    "いんしゅ": "n4-details-chunk-0.json",
    "うけつけ": "n4-details-chunk-0.json",
    "うそ": "n4-details-chunk-0.json",
    "うち": "n4-details-chunk-0.json",
    "うちがわ": "n4-details-chunk-0.json",
    "うで": "n4-details-chunk-0.json",
    "うら": "n4-details-chunk-0.json",
    "うりば": "n4-details-chunk-0.json",
    "うん": "n4-details-chunk-0.json",
    "うんてん": "n4-details-chunk-0.json",
    "うんてんしゅ": "n4-details-chunk-0.json",
    "うんどう": "n4-details-chunk-0.json",
    "うんどうかい": "n4-details-chunk-0.json",
    "えいかいわ": "n4-details-chunk-0.json",
    "えいが": "n4-details-chunk-0.json",
    "えいぎょう": "n4-details-chunk-0.json",
    "えきいん": "n4-details-chunk-0.json",
    "えだ": "n4-details-chunk-0.json",
    "えんりょ": "n4-details-chunk-0.json",
    "おいわい": "n4-details-chunk-0.json",
    "おうだんほどう": "n4-details-chunk-0.json",
    "おおあめ": "n4-details-chunk-0.json",
    "おおゆき": "n4-details-chunk-0.json",
    "おかげ": "n4-details-chunk-0.json",
    "おく": "n4-details-chunk-0.json",
    "おくさま": "n4-details-chunk-0.json",
    "おくじょう": "n4-details-chunk-0.json",
    "おくりもの": "n4-details-chunk-0.json",
    "おこさん": "n4-details-chunk-0.json",
    "おしいれ": "n4-details-chunk-0.json",
    "おしまい": "n4-details-chunk-0.json",
    "おじ": "n4-details-chunk-0.json",
    "おじょうさん": "n4-details-chunk-0.json",
    "おたく": "n4-details-chunk-0.json",
    "おっと": "n4-details-chunk-0.json",
    "おつり": "n4-details-chunk-0.json",
    "おてあらい": "n4-details-chunk-0.json",
    "おでかけ": "n4-details-chunk-0.json",
    "おと": "n4-details-chunk-0.json",
    "おとしもの": "n4-details-chunk-0.json",
    "おとしより": "n4-details-chunk-0.json",
    "おどり": "n4-details-chunk-0.json",
    "おば": "n4-details-chunk-0.json",
    "おまつり": "n4-details-chunk-0.json",
    "おみまい": "n4-details-chunk-0.json",
    "おもちゃ": "n4-details-chunk-0.json",
    "おもて": "n4-details-chunk-0.json",
    "おわり": "n4-details-chunk-0.json",
    "かい": "n4-details-chunk-0.json",
    "かいがん": "n4-details-chunk-0.json",
    "かいぎ": "n4-details-chunk-0.json",
    "かいじょう": "n4-details-chunk-0.json",
    "かいわ": "n4-details-chunk-0.json",
    "かえり": "n4-details-chunk-0.json",
    "かがく": "n4-details-chunk-0.json",
    "かがみ": "n4-details-chunk-0.json",
    "かきかた": "n4-details-chunk-0.json",
    "かぎ": "n4-details-chunk-0.json",
    "かざり": "n4-details-chunk-0.json",
    "かしゅ": "n4-details-chunk-0.json",
    "かじ": "n4-details-chunk-0.json",
    "かた": "n4-details-chunk-0.json",
    "かたかな": "n4-details-chunk-0.json",
    "かたち": "n4-details-chunk-0.json",
    "かちょう": "n4-details-chunk-0.json",
    "かっこう": "n4-details-chunk-0.json",
    "かてい": "n4-details-chunk-0.json",
    "かない": "n4-details-chunk-0.json",
    "かねもち": "n4-details-chunk-1.json",
    "かべ": "n4-details-chunk-1.json",
    "かみ": "n4-details-chunk-1.json",
    "かわり": "n4-details-chunk-1.json",
    "かんがえかた": "n4-details-chunk-1.json",
    "かんけい": "n4-details-chunk-1.json",
    "かんこう": "n4-details-chunk-1.json",
    "かんごし": "n4-details-chunk-1.json",
    "かんたん": "n4-details-chunk-1.json",
    "がいこく": "n4-details-chunk-1.json",
    "がいしょく": "n4-details-chunk-1.json",
    "がいぶ": "n4-details-chunk-1.json",
    "がわ": "n4-details-chunk-1.json",
    "き": "n4-details-chunk-1.json",
    "きかい": "n4-details-chunk-1.json",
    "きかん": "n4-details-chunk-1.json",
    "ききとり": "n4-details-chunk-1.json",
    "きけん": "n4-details-chunk-1.json",
    "きしゃ": "n4-details-chunk-1.json",
    "きせつ": "n4-details-chunk-1.json",
    "きそく": "n4-details-chunk-1.json",
    "きぬ": "n4-details-chunk-1.json",
    "きぶん": "n4-details-chunk-1.json",
    "きもち": "n4-details-chunk-1.json",
    "きもの": "n4-details-chunk-1.json",
    "きゃく": "n4-details-chunk-1.json",
    "きゅうこう": "n4-details-chunk-1.json",
    "きょういく": "n4-details-chunk-1.json",
    "きょうかい": "n4-details-chunk-1.json",
    "きょうみ": "n4-details-chunk-1.json",
    "きんぎょ": "n4-details-chunk-1.json",
    "きんじょ": "n4-details-chunk-1.json",
    "ぎじゅつ": "n4-details-chunk-1.json",
    "くうき": "n4-details-chunk-1.json",
    "くうこう": "n4-details-chunk-1.json",
    "くさ": "n4-details-chunk-1.json",
    "くび": "n4-details-chunk-1.json",
    "くも": "n4-details-chunk-1.json",
    "くもり": "n4-details-chunk-1.json",
    "くやくしょ": "n4-details-chunk-1.json",
    "ぐあい": "n4-details-chunk-1.json",
    "ぐんじん": "n4-details-chunk-1.json",
    "け": "n4-details-chunk-1.json",
    "けいかく": "n4-details-chunk-1.json",
    "けいけん": "n4-details-chunk-1.json",
    "けいさつ": "n4-details-chunk-1.json",
    "けいざい": "n4-details-chunk-1.json",
    "けが": "n4-details-chunk-1.json",
    "けしき": "n4-details-chunk-1.json",
    "けしゴム": "n4-details-chunk-1.json",
    "けっせき": "n4-details-chunk-1.json",
    "けんか": "n4-details-chunk-1.json",
    "けんきゅうしつ": "n4-details-chunk-1.json",
    "けんぶつ": "n4-details-chunk-1.json",
    "げしゅく": "n4-details-chunk-1.json",
    "げんいん": "n4-details-chunk-1.json",
    "げんかん": "n4-details-chunk-1.json",
    "こ": "n4-details-chunk-1.json",
    "こいぬ": "n4-details-chunk-1.json",
    "こう": "n4-details-chunk-1.json",
    "こうかい": "n4-details-chunk-1.json",
    "こうがい": "n4-details-chunk-1.json",
    "こうぎ": "n4-details-chunk-1.json",
    "こうぎょう": "n4-details-chunk-1.json",
    "こうこう": "n4-details-chunk-1.json",
    "こうこうせい": "n4-details-chunk-1.json",
    "こうさてん": "n4-details-chunk-1.json",
    "こうじ": "n4-details-chunk-1.json",
    "こうじょう": "n4-details-chunk-1.json",
    "こうちょう": "n4-details-chunk-1.json",
    "こうつう": "n4-details-chunk-1.json",
    "こうどう": "n4-details-chunk-1.json",
    "こうば": "n4-details-chunk-1.json",
    "こうむいん": "n4-details-chunk-1.json",
    "こおり": "n4-details-chunk-1.json",
    "こくさい": "n4-details-chunk-1.json",
    "こくさん": "n4-details-chunk-1.json",
    "こくない": "n4-details-chunk-1.json",
    "こくみん": "n4-details-chunk-1.json",
    "こくりつ": "n4-details-chunk-1.json",
    "ここのつ": "n4-details-chunk-1.json",
    "こころ": "n4-details-chunk-1.json",
    "こしょう": "n4-details-chunk-1.json",
    "こじん": "n4-details-chunk-1.json",
    "こたえ": "n4-details-chunk-1.json",
    "こと": "n4-details-chunk-1.json",
    "ことば": "n4-details-chunk-1.json",
    "ことり": "n4-details-chunk-1.json",
    "こねこ": "n4-details-chunk-1.json",
    "このあいだ": "n4-details-chunk-1.json",
    "このごろ": "n4-details-chunk-1.json",
    "このは": "n4-details-chunk-1.json",
    "このへん": "n4-details-chunk-1.json",
    "こめ": "n4-details-chunk-1.json",
    "ころ": "n4-details-chunk-1.json",
    "こんかい": "n4-details-chunk-1.json",
    "こんど": "n4-details-chunk-1.json",
    "こんや": "n4-details-chunk-1.json",
    "ご": "n4-details-chunk-1.json",
    "ごぞんじ": "n4-details-chunk-1.json",
    "ごちそう": "n4-details-chunk-2.json",
    "ごみ": "n4-details-chunk-2.json",
    "さいきん": "n4-details-chunk-2.json",
    "さいご": "n4-details-chunk-2.json",
    "さいしょ": "n4-details-chunk-2.json",
    "さか": "n4-details-chunk-2.json",
    "さくひん": "n4-details-chunk-2.json",
    "さくら": "n4-details-chunk-2.json",
    "さっき": "n4-details-chunk-2.json",
    "さとう": "n4-details-chunk-2.json",
    "さま": "n4-details-chunk-2.json",
    "さらいげつ": "n4-details-chunk-2.json",
    "さらいしゅう": "n4-details-chunk-2.json",
    "さらいねん": "n4-details-chunk-2.json",
    "さん": "n4-details-chunk-2.json",
    "さんかく": "n4-details-chunk-2.json",
    "さんぎょう": "n4-details-chunk-2.json",
    "さんすう": "n4-details-chunk-2.json",
    "さんせい": "n4-details-chunk-2.json",
    "ざんねん": "n4-details-chunk-2.json",
    "し": "n4-details-chunk-2.json",
    "しあい": "n4-details-chunk-2.json",
    "しかた": "n4-details-chunk-2.json",
    "しけん": "n4-details-chunk-2.json",
    "した": "n4-details-chunk-2.json",
    "したぎ": "n4-details-chunk-2.json",
    "したく": "n4-details-chunk-2.json",
    "しっぱい": "n4-details-chunk-2.json",
    "しつない": "n4-details-chunk-2.json",
    "しつもん": "n4-details-chunk-2.json",
    "しつれい": "n4-details-chunk-2.json",
    "しない": "n4-details-chunk-2.json",
    "しなもの": "n4-details-chunk-2.json",
    "しはらい": "n4-details-chunk-2.json",
    "しま": "n4-details-chunk-2.json",
    "しまい": "n4-details-chunk-2.json",
    "しみん": "n4-details-chunk-2.json",
    "しゃかい": "n4-details-chunk-2.json",
    "しゃちょう": "n4-details-chunk-2.json",
    "しゃどう": "n4-details-chunk-2.json",
    "しやくしょ": "n4-details-chunk-2.json",
    "しゅうかん": "n4-details-chunk-2.json",
    "しゅじん": "n4-details-chunk-2.json",
    "しゅっせき": "n4-details-chunk-2.json",
    "しゅっぱつ": "n4-details-chunk-2.json",
    "しゅみ": "n4-details-chunk-2.json",
    "しょうかい": "n4-details-chunk-2.json",
    "しょうがっこう": "n4-details-chunk-2.json",
    "しょうがつ": "n4-details-chunk-2.json",
    "しょうせつ": "n4-details-chunk-2.json",
    "しょうたい": "n4-details-chunk-2.json",
    "しょうゆ": "n4-details-chunk-2.json",
    "しょうらい": "n4-details-chunk-2.json",
    "しょくじ": "n4-details-chunk-2.json",
    "しょくりょうひん": "n4-details-chunk-2.json",
    "しんねん": "n4-details-chunk-2.json",
    "しんぱい": "n4-details-chunk-2.json",
    "じ": "n4-details-chunk-2.json",
    "じこ": "n4-details-chunk-2.json",
    "じしん": "n4-details-chunk-2.json",
    "じだい": "n4-details-chunk-2.json",
    "じてん": "n4-details-chunk-2.json",
    "じてんしゃ": "n4-details-chunk-2.json",
    "じどう": "n4-details-chunk-2.json",
    "じどうしゃ": "n4-details-chunk-2.json",
    "じびき": "n4-details-chunk-2.json",
    "じぶん": "n4-details-chunk-2.json",
    "じむしょ": "n4-details-chunk-2.json",
    "じゃま": "n4-details-chunk-2.json",
    "じゅう": "n4-details-chunk-2.json",
    "じゅうしょ": "n4-details-chunk-2.json",
    "じゅうどう": "n4-details-chunk-2.json",
    "じゅぎょう": "n4-details-chunk-2.json",
    "じゅんび": "n4-details-chunk-2.json",
    "じゆう": "n4-details-chunk-2.json",
    "じょせい": "n4-details-chunk-2.json",
    "じん": "n4-details-chunk-2.json",
    "じんこう": "n4-details-chunk-2.json",
    "じんじゃ": "n4-details-chunk-2.json",
    "すいえい": "n4-details-chunk-2.json",
    "すいどう": "n4-details-chunk-2.json",
    "すうがく": "n4-details-chunk-2.json",
    "すな": "n4-details-chunk-2.json",
    "すり": "n4-details-chunk-2.json",
    "せい": "n4-details-chunk-2.json",
    "せいかつ": "n4-details-chunk-2.json",
    "せいさん": "n4-details-chunk-2.json",
    "せいじ": "n4-details-chunk-2.json",
    "せいよう": "n4-details-chunk-2.json",
    "せかい": "n4-details-chunk-2.json",
    "せかいじゅう": "n4-details-chunk-2.json",
    "せき": "n4-details-chunk-2.json",
    "せつめい": "n4-details-chunk-2.json",
    "せなか": "n4-details-chunk-2.json",
    "せびろ": "n4-details-chunk-2.json",
    "せわ": "n4-details-chunk-2.json",
    "せん": "n4-details-chunk-2.json",
    "せんしゅ": "n4-details-chunk-2.json",
    "せんせんげつ": "n4-details-chunk-2.json",
    "せんせんしゅう": "n4-details-chunk-2.json",
    "せんそう": "n4-details-chunk-3.json",
    "せんたく": "n4-details-chunk-3.json",
    "せんぱい": "n4-details-chunk-3.json",
    "せんもん": "n4-details-chunk-3.json",
    "ぜんこく": "n4-details-chunk-3.json",
    "ぜんたい": "n4-details-chunk-3.json",
    "ぜんぶ": "n4-details-chunk-3.json",
    "そうじ": "n4-details-chunk-3.json",
    "そうたい": "n4-details-chunk-3.json",
    "そうだん": "n4-details-chunk-3.json",
    "そつぎょう": "n4-details-chunk-3.json",
    "そとがわ": "n4-details-chunk-3.json",
    "そば": "n4-details-chunk-3.json",
    "そふ": "n4-details-chunk-3.json",
    "そぼ": "n4-details-chunk-3.json",
    "たいいん": "n4-details-chunk-3.json",
    "たいしかん": "n4-details-chunk-3.json",
    "たいふう": "n4-details-chunk-3.json",
    "たいへん": "n4-details-chunk-3.json",
    "たかい": "n4-details-chunk-3.json",
    "たけ": "n4-details-chunk-3.json",
    "たすう": "n4-details-chunk-3.json",
    "たたみ": "n4-details-chunk-3.json",
    "ただいま": "n4-details-chunk-3.json",
    "たて": "n4-details-chunk-3.json",
    "たな": "n4-details-chunk-3.json",
    "たのしみ": "n4-details-chunk-3.json",
    "たぶん": "n4-details-chunk-3.json",
    "たべすぎ": "n4-details-chunk-3.json",
    "ため": "n4-details-chunk-3.json",
    "だい": "n4-details-chunk-3.json",
    "だいがくせい": "n4-details-chunk-3.json",
    "だいじ": "n4-details-chunk-3.json",
    "だいたい": "n4-details-chunk-3.json",
    "だめ": "n4-details-chunk-3.json",
    "だんせい": "n4-details-chunk-3.json",
    "ち": "n4-details-chunk-3.json",
    "ちから": "n4-details-chunk-3.json",
    "ちず": "n4-details-chunk-3.json",
    "ちちおや": "n4-details-chunk-3.json",
    "ちゃいろ": "n4-details-chunk-3.json",
    "ちゃわん": "n4-details-chunk-3.json",
    "ちゅう": "n4-details-chunk-3.json",
    "ちゅうい": "n4-details-chunk-3.json",
    "ちゅうがくせい": "n4-details-chunk-3.json",
    "ちゅうがっこう": "n4-details-chunk-3.json",
    "ちゅうし": "n4-details-chunk-3.json",
    "ちゅうしゃ": "n4-details-chunk-3.json",
    "ちゅうしゃじょう": "n4-details-chunk-3.json",
    "ちり": "n4-details-chunk-3.json",
    "つき": "n4-details-chunk-3.json",
    "つごう": "n4-details-chunk-3.json",
    "つま": "n4-details-chunk-3.json",
    "つめ": "n4-details-chunk-3.json",
    "つもり": "n4-details-chunk-3.json",
    "つゆ": "n4-details-chunk-3.json",
    "ていねい": "n4-details-chunk-3.json",
    "てぶくろ": "n4-details-chunk-3.json",
    "てもと": "n4-details-chunk-3.json",
    "てら": "n4-details-chunk-3.json",
    "てん": "n4-details-chunk-3.json",
    "てんいん": "n4-details-chunk-3.json",
    "てんきよほう": "n4-details-chunk-3.json",
    "てんらんかい": "n4-details-chunk-3.json",
    "でいりぐち": "n4-details-chunk-3.json",
    "でんきだい": "n4-details-chunk-3.json",
    "でんとう": "n4-details-chunk-3.json",
    "でんぽう": "n4-details-chunk-3.json",
    "と": "n4-details-chunk-3.json",
    "とお": "n4-details-chunk-3.json",
    "とおく": "n4-details-chunk-3.json",
    "とおり": "n4-details-chunk-3.json",
    "とき": "n4-details-chunk-3.json",
    "とこや": "n4-details-chunk-3.json",
    "とちゅう": "n4-details-chunk-3.json",
    "とっきゅう": "n4-details-chunk-3.json",
    "ど": "n4-details-chunk-3.json",
    "どうぐ": "n4-details-chunk-3.json",
    "どうぶつえん": "n4-details-chunk-3.json",
    "どろぼう": "n4-details-chunk-3.json",
    "ないぶ": "n4-details-chunk-3.json",
    "ななつ": "n4-details-chunk-3.json",
    "なまビール": "n4-details-chunk-3.json",
    "なんど": "n4-details-chunk-3.json",
    "におい": "n4-details-chunk-3.json",
    "にくや": "n4-details-chunk-3.json",
    "にち": "n4-details-chunk-3.json",
    "にっき": "n4-details-chunk-3.json",
    "にもつ": "n4-details-chunk-3.json",
    "にゅういん": "n4-details-chunk-3.json",
    "にゅうがく": "n4-details-chunk-3.json",
    "にゅうしゃ": "n4-details-chunk-3.json",
    "にん": "n4-details-chunk-3.json",
    "にんぎょう": "n4-details-chunk-3.json",
    "にんじん": "n4-details-chunk-3.json",
    "ねだん": "n4-details-chunk-3.json",
    "ねつ": "n4-details-chunk-3.json",
    "ねぼう": "n4-details-chunk-3.json",
    "ねん": "n4-details-chunk-3.json",
    "ねんだい": "n4-details-chunk-3.json",
    "のど": "n4-details-chunk-4.json",
    "のみすぎ": "n4-details-chunk-4.json",
    "のりかえ": "n4-details-chunk-4.json",
    "のりもの": "n4-details-chunk-4.json",
    "は": "n4-details-chunk-4.json",
    "はい": "n4-details-chunk-4.json",
    "はいしゃ": "n4-details-chunk-4.json",
    "はくさい": "n4-details-chunk-4.json",
    "はこ": "n4-details-chunk-4.json",
    "はし": "n4-details-chunk-4.json",
    "はじまり": "n4-details-chunk-4.json",
    "はず": "n4-details-chunk-4.json",
    "はつおん": "n4-details-chunk-4.json",
    "はなみ": "n4-details-chunk-4.json",
    "はね": "n4-details-chunk-4.json",
    "はやし": "n4-details-chunk-4.json",
    "はれ": "n4-details-chunk-4.json",
    "はん": "n4-details-chunk-4.json",
    "はんたい": "n4-details-chunk-4.json",
    "はんぶん": "n4-details-chunk-4.json",
    "ばあい": "n4-details-chunk-4.json",
    "ばしょ": "n4-details-chunk-4.json",
    "ばん": "n4-details-chunk-4.json",
    "ばんぐみ": "n4-details-chunk-4.json",
    "ばんせん": "n4-details-chunk-4.json",
    "ひ": "n4-details-chunk-4.json",
    "ひかり": "n4-details-chunk-4.json",
    "ひきだし": "n4-details-chunk-4.json",
    "ひげ": "n4-details-chunk-4.json",
    "ひこうじょう": "n4-details-chunk-4.json",
    "ひさしぶり": "n4-details-chunk-4.json",
    "ひだり": "n4-details-chunk-4.json",
    "ひつよう": "n4-details-chunk-4.json",
    "ひとつき": "n4-details-chunk-4.json",
    "ひゃっかてん": "n4-details-chunk-4.json",
    "ひらがな": "n4-details-chunk-4.json",
    "ひるま": "n4-details-chunk-4.json",
    "ひるやすみ": "n4-details-chunk-4.json",
    "ひろさ": "n4-details-chunk-4.json",
    "びじゅつかん": "n4-details-chunk-4.json",
    "びっくり": "n4-details-chunk-4.json",
    "びょう": "n4-details-chunk-4.json",
    "ふうとう": "n4-details-chunk-4.json",
    "ふくざつ": "n4-details-chunk-4.json",
    "ふくしゅう": "n4-details-chunk-4.json",
    "ふとん": "n4-details-chunk-4.json",
    "ふね": "n4-details-chunk-4.json",
    "ふべん": "n4-details-chunk-4.json",
    "ふろ": "n4-details-chunk-4.json",
    "ふん": "n4-details-chunk-4.json",
    "ぶたにく": "n4-details-chunk-4.json",
    "ぶちょう": "n4-details-chunk-4.json",
    "ぶどう": "n4-details-chunk-4.json",
    "ぶんか": "n4-details-chunk-4.json",
    "ぶんがく": "n4-details-chunk-4.json",
    "ぶんしょ": "n4-details-chunk-4.json",
    "ぶんしょう": "n4-details-chunk-4.json",
    "ぶんぽう": "n4-details-chunk-4.json",
    "へた": "n4-details-chunk-4.json",
    "へん": "n4-details-chunk-4.json",
    "へんじ": "n4-details-chunk-4.json",
    "べつ": "n4-details-chunk-4.json",
    "ほうそう": "n4-details-chunk-4.json",
    "ほうりつ": "n4-details-chunk-4.json",
    "ほし": "n4-details-chunk-4.json",
    "ほとんど": "n4-details-chunk-4.json",
    "ほね": "n4-details-chunk-4.json",
    "ほんき": "n4-details-chunk-4.json",
    "ほんだな": "n4-details-chunk-4.json",
    "ほんとう": "n4-details-chunk-4.json",
    "ほんや": "n4-details-chunk-4.json",
    "ぼうえき": "n4-details-chunk-4.json",
    "ぼうし": "n4-details-chunk-4.json",
    "ぼく": "n4-details-chunk-4.json",
    "まいつき": "n4-details-chunk-4.json",
    "まいとし": "n4-details-chunk-4.json",
    "まご": "n4-details-chunk-4.json",
    "まじめ": "n4-details-chunk-4.json",
    "まどぐち": "n4-details-chunk-4.json",
    "まどガラス": "n4-details-chunk-4.json",
    "まん": "n4-details-chunk-4.json",
    "まんが": "n4-details-chunk-4.json",
    "まんなか": "n4-details-chunk-4.json",
    "まんねんひつ": "n4-details-chunk-4.json",
    "みな": "n4-details-chunk-4.json",
    "みなと": "n4-details-chunk-4.json",
    "むかし": "n4-details-chunk-4.json",
    "むこう": "n4-details-chunk-4.json",
    "むし": "n4-details-chunk-4.json",
    "むすこさん": "n4-details-chunk-4.json",
    "むすめ": "n4-details-chunk-4.json",
    "むすめさん": "n4-details-chunk-4.json",
    "むっつ": "n4-details-chunk-4.json",
    "むら": "n4-details-chunk-4.json",
    "むり": "n4-details-chunk-4.json",
    "もちかえり": "n4-details-chunk-4.json",
    "もめん": "n4-details-chunk-4.json",
    "もり": "n4-details-chunk-4.json",
    "や": "n4-details-chunk-4.json",
    "やかん": "n4-details-chunk-4.json",
    "やくそく": "n4-details-chunk-5.json",
    "やっつ": "n4-details-chunk-5.json",
    "やまみち": "n4-details-chunk-5.json",
    "ゆ": "n4-details-chunk-5.json",
    "ゆうしょく": "n4-details-chunk-5.json",
    "ゆうびんきょく": "n4-details-chunk-5.json",
    "ゆうべ": "n4-details-chunk-5.json",
    "ゆうめい": "n4-details-chunk-5.json",
    "ゆしゅつ": "n4-details-chunk-5.json",
    "ゆにゅう": "n4-details-chunk-5.json",
    "ゆび": "n4-details-chunk-5.json",
    "ゆびわ": "n4-details-chunk-5.json",
    "ゆめ": "n4-details-chunk-5.json",
    "よい": "n4-details-chunk-5.json",
    "ようい": "n4-details-chunk-5.json",
    "ようじ": "n4-details-chunk-5.json",
    "よしゅう": "n4-details-chunk-5.json",
    "よてい": "n4-details-chunk-5.json",
    "よみかた": "n4-details-chunk-5.json",
    "よみもの": "n4-details-chunk-5.json",
    "よやく": "n4-details-chunk-5.json",
    "りゆう": "n4-details-chunk-5.json",
    "りょうしん": "n4-details-chunk-5.json",
    "りょうほう": "n4-details-chunk-5.json",
    "りょかん": "n4-details-chunk-5.json",
    "りょこう": "n4-details-chunk-5.json",
    "りよう": "n4-details-chunk-5.json",
    "りんご": "n4-details-chunk-5.json",
    "るす": "n4-details-chunk-5.json",
    "れい": "n4-details-chunk-5.json",
    "れいぞうこ": "n4-details-chunk-5.json",
    "れいぼう": "n4-details-chunk-5.json",
    "れきし": "n4-details-chunk-5.json",
    "れっしゃ": "n4-details-chunk-5.json",
    "れんしゅう": "n4-details-chunk-5.json",
    "れんらく": "n4-details-chunk-5.json",
    "ろうか": "n4-details-chunk-5.json",
    "ろうじん": "n4-details-chunk-5.json",
    "わけ": "n4-details-chunk-5.json",
    "わすれもの": "n4-details-chunk-5.json",
    "わたくし": "n4-details-chunk-5.json",
    "わたし": "n4-details-chunk-5.json",
    "アイロン": "n4-details-chunk-5.json",
    "アクセサリー": "n4-details-chunk-5.json",
    "アジア": "n4-details-chunk-5.json",
    "アナウンサー": "n4-details-chunk-5.json",
    "アニメ": "n4-details-chunk-5.json",
    "アフリカ": "n4-details-chunk-5.json",
    "アメリカ": "n4-details-chunk-5.json",
    "アルコール": "n4-details-chunk-5.json",
    "アルバイト": "n4-details-chunk-5.json",
    "イヤリング": "n4-details-chunk-5.json",
    "エアコン": "n4-details-chunk-5.json",
    "エスカレーター": "n4-details-chunk-5.json",
    "オートバイ": "n4-details-chunk-5.json",
    "カレー": "n4-details-chunk-5.json",
    "カーテン": "n4-details-chunk-5.json",
    "ガス": "n4-details-chunk-5.json",
    "ガスだい": "n4-details-chunk-5.json",
    "ガソリン": "n4-details-chunk-5.json",
    "ガソリンスタンド": "n4-details-chunk-5.json",
    "ガラス": "n4-details-chunk-5.json",
    "キッチン": "n4-details-chunk-5.json",
    "キロ": "n4-details-chunk-5.json",
    "キログラム": "n4-details-chunk-5.json",
    "キロメートル": "n4-details-chunk-5.json",
    "グラム": "n4-details-chunk-5.json",
    "ケーキ": "n4-details-chunk-5.json",
    "ゲーム": "n4-details-chunk-5.json",
    "コンサート": "n4-details-chunk-5.json",
    "コンピューター": "n4-details-chunk-5.json",
    "サイン": "n4-details-chunk-5.json",
    "サラダ": "n4-details-chunk-5.json",
    "サンダル": "n4-details-chunk-5.json",
    "サンドイッチ": "n4-details-chunk-5.json",
    "ジャム": "n4-details-chunk-5.json",
    "ジュース": "n4-details-chunk-5.json",
    "スクリーン": "n4-details-chunk-5.json",
    "ステレオ": "n4-details-chunk-5.json",
    "ステーキ": "n4-details-chunk-5.json",
    "スピーカー": "n4-details-chunk-5.json",
    "スピーチ": "n4-details-chunk-5.json",
    "スピード": "n4-details-chunk-5.json",
    "スリッパ": "n4-details-chunk-5.json",
    "スーツ": "n4-details-chunk-5.json",
    "スーツケース": "n4-details-chunk-5.json",
    "スーパー": "n4-details-chunk-5.json",
    "セット": "n4-details-chunk-5.json",
    "ソフト": "n4-details-chunk-5.json",
    "タイプ": "n4-details-chunk-5.json",
    "ダンス": "n4-details-chunk-5.json",
    "チェック": "n4-details-chunk-5.json",
    "チケット": "n4-details-chunk-5.json",
    "テキスト": "n4-details-chunk-5.json",
    "テニス": "n4-details-chunk-5.json",
    "テープレコーダー": "n4-details-chunk-5.json",
    "トラック": "n4-details-chunk-5.json",
    "ドラマ": "n4-details-chunk-5.json",
    "ドレス": "n4-details-chunk-5.json",
    "ニュース": "n4-details-chunk-5.json",
    "ハンバーグ": "n4-details-chunk-6.json",
    "バケツ": "n4-details-chunk-6.json",
    "バター": "n4-details-chunk-6.json",
    "パソコン": "n4-details-chunk-6.json",
    "パンや": "n4-details-chunk-6.json",
    "パージ": "n4-details-chunk-6.json",
    "パーティー": "n4-details-chunk-6.json",
    "パートタイム": "n4-details-chunk-6.json",
    "ビール": "n4-details-chunk-6.json",
    "ピアノ": "n4-details-chunk-6.json",
    "ピクニック": "n4-details-chunk-6.json",
    "ピンク": "n4-details-chunk-6.json",
    "フィルム": "n4-details-chunk-6.json",
    "フォーク": "n4-details-chunk-6.json",
    "プリント": "n4-details-chunk-6.json",
    "プレゼント": "n4-details-chunk-6.json",
    "プール": "n4-details-chunk-6.json",
    "ベッド": "n4-details-chunk-6.json",
    "ベル": "n4-details-chunk-6.json",
    "ペット": "n4-details-chunk-6.json",
    "ページ": "n4-details-chunk-6.json",
    "ボート": "n4-details-chunk-6.json",
    "ボール": "n4-details-chunk-6.json",
    "ポスト": "n4-details-chunk-6.json",
    "マスク": "n4-details-chunk-6.json",
    "マッチ": "n4-details-chunk-6.json",
    "メロン": "n4-details-chunk-6.json",
    "メートル": "n4-details-chunk-6.json",
    "ラジカセ": "n4-details-chunk-6.json",
    "レコード": "n4-details-chunk-6.json",
    "レジ": "n4-details-chunk-6.json",
    "レベル": "n4-details-chunk-6.json",
    "レポート": "n4-details-chunk-6.json",
    "ワイシャツ": "n4-details-chunk-6.json",
    "ワンピース": "n4-details-chunk-6.json",
    "ワープロ": "n4-details-chunk-6.json",
    "あれ": "n4-details-chunk-6.json",
    "かのじょ": "n4-details-chunk-6.json",
    "かれ": "n4-details-chunk-6.json",
    "かれら": "n4-details-chunk-6.json",
    "きみ": "n4-details-chunk-6.json",
    "てまえ": "n4-details-chunk-6.json",
    "なん": "n4-details-chunk-6.json",
    "あ-う": "n4-details-chunk-6.json",
    "あ-く": "n4-details-chunk-6.json",
    "あつま-る": "n4-details-chunk-6.json",
    "あつ-める": "n4-details-chunk-6.json",
    "あやま-る": "n4-details-chunk-6.json",
    "い-きる": "n4-details-chunk-6.json",
    "いじ-める": "n4-details-chunk-6.json",
    "いそ-ぐ": "n4-details-chunk-6.json",
    "いた-す": "n4-details-chunk-6.json",
    "いただ-く": "n4-details-chunk-6.json",
    "いの-る": "n4-details-chunk-6.json",
    "いらっしゃ-る": "n4-details-chunk-6.json",
    "いわ-う": "n4-details-chunk-6.json",
    "う-える": "n4-details-chunk-6.json",
    "うかが-う": "n4-details-chunk-6.json",
    "う-ける": "n4-details-chunk-6.json",
    "うご-く": "n4-details-chunk-6.json",
    "う-つ": "n4-details-chunk-6.json",
    "うつ-す": "n4-details-chunk-6.json",
    "えら-ぶ": "n4-details-chunk-6.json",
    "おいでに なる": "n4-details-chunk-6.json",
    "おく-る": "n4-details-chunk-6.json",
    "おく-れる": "n4-details-chunk-6.json",
    "おこ-す": "n4-details-chunk-6.json",
    "おこ-る": "n4-details-chunk-6.json",
    "お-ちる": "n4-details-chunk-6.json",
    "おっしゃ-る": "n4-details-chunk-6.json",
    "おと-す": "n4-details-chunk-6.json",
    "おど-る": "n4-details-chunk-6.json",
    "おどろ-く": "n4-details-chunk-6.json",
    "おもいだ-す": "n4-details-chunk-6.json",
    "おも-う": "n4-details-chunk-6.json",
    "おやすみに なる": "n4-details-chunk-6.json",
    "お-りる": "n4-details-chunk-6.json",
    "お-る": "n4-details-chunk-6.json",
    "お-れる": "n4-details-chunk-6.json",
    "か-う": "n4-details-chunk-6.json",
    "か-える": "n4-details-chunk-6.json",
    "かか-る": "n4-details-chunk-6.json",
    "か-ける": "n4-details-chunk-6.json",
    "かざ-る": "n4-details-chunk-6.json",
    "かたづ-ける": "n4-details-chunk-6.json",
    "か-つ": "n4-details-chunk-6.json",
    "か-む": "n4-details-chunk-6.json",
    "かよ-う": "n4-details-chunk-6.json",
    "かわ-く": "n4-details-chunk-6.json",
    "かわ-る": "n4-details-chunk-6.json",
    "かんが-える": "n4-details-chunk-6.json",
    "がまんする": "n4-details-chunk-6.json",
    "がんば-る": "n4-details-chunk-6.json",
    "きこ-える": "n4-details-chunk-6.json",
    "きま-る": "n4-details-chunk-6.json",
    "き-める": "n4-details-chunk-6.json",
    "きる": "n4-details-chunk-6.json",
    "き-る": "n4-details-chunk-6.json",
    "くださ-る": "n4-details-chunk-6.json",
    "くも-る": "n4-details-chunk-6.json",
    "くら-べる": "n4-details-chunk-7.json",
    "く-れる": "n4-details-chunk-7.json",
    "こ-む": "n4-details-chunk-7.json",
    "ころ-ぶ": "n4-details-chunk-7.json",
    "こわ-す": "n4-details-chunk-7.json",
    "こわ-れる": "n4-details-chunk-7.json",
    "ござ-る": "n4-details-chunk-7.json",
    "ごらんになる": "n4-details-chunk-7.json",
    "さが-す": "n4-details-chunk-7.json",
    "さが-る": "n4-details-chunk-7.json",
    "さ-げる": "n4-details-chunk-7.json",
    "さしあ-げる": "n4-details-chunk-7.json",
    "さ-す": "n4-details-chunk-7.json",
    "さわ-ぐ": "n4-details-chunk-7.json",
    "さわ-る": "n4-details-chunk-7.json",
    "しか-る": "n4-details-chunk-7.json",
    "しっかり": "n4-details-chunk-7.json",
    "しま-う": "n4-details-chunk-7.json",
    "しら-せる": "n4-details-chunk-7.json",
    "しら-べる": "n4-details-chunk-7.json",
    "し-る": "n4-details-chunk-7.json",
    "す-ぎる": "n4-details-chunk-7.json",
    "す-く": "n4-details-chunk-7.json",
    "すす-む": "n4-details-chunk-7.json",
    "す-てる": "n4-details-chunk-7.json",
    "すべ-る": "n4-details-chunk-7.json",
    "す-る": "n4-details-chunk-7.json",
    "そだ-てる": "n4-details-chunk-7.json",
    "ぞん-じる": "n4-details-chunk-7.json",
    "たお-れる": "n4-details-chunk-7.json",
    "た-す": "n4-details-chunk-7.json",
    "たず-ねる": "n4-details-chunk-7.json",
    "た-つ": "n4-details-chunk-7.json",
    "た-てる": "n4-details-chunk-7.json",
    "たの-む": "n4-details-chunk-7.json",
    "た-りる": "n4-details-chunk-7.json",
    "ちが-う": "n4-details-chunk-7.json",
    "つかま-える": "n4-details-chunk-7.json",
    "つか-れる": "n4-details-chunk-7.json",
    "つ-く": "n4-details-chunk-7.json",
    "つ-ける": "n4-details-chunk-7.json",
    "つた-える": "n4-details-chunk-7.json",
    "つつ-む": "n4-details-chunk-7.json",
    "つづ-く": "n4-details-chunk-7.json",
    "つづ-ける": "n4-details-chunk-7.json",
    "つと-める": "n4-details-chunk-7.json",
    "つも-る": "n4-details-chunk-7.json",
    "つ-る": "n4-details-chunk-7.json",
    "つ-れる": "n4-details-chunk-7.json",
    "てつだ-う": "n4-details-chunk-7.json",
    "でか-ける": "n4-details-chunk-7.json",
    "で-きる": "n4-details-chunk-7.json",
    "とお-る": "n4-details-chunk-7.json",
    "と-じる": "n4-details-chunk-7.json",
    "とど-く": "n4-details-chunk-7.json",
    "とど-ける": "n4-details-chunk-7.json",
    "とま-る": "n4-details-chunk-7.json",
    "と-める": "n4-details-chunk-7.json",
    "とりか-える": "n4-details-chunk-7.json",
    "と-る": "n4-details-chunk-7.json",
    "なお-す": "n4-details-chunk-7.json",
    "なおす": "n4-details-chunk-7.json",
    "なおる": "n4-details-chunk-7.json",
    "なお-る": "n4-details-chunk-7.json",
    "なが-れる": "n4-details-chunk-7.json",
    "な-く": "n4-details-chunk-7.json",
    "なく-す": "n4-details-chunk-7.json",
    "なくな-る": "n4-details-chunk-7.json",
    "な-げる": "n4-details-chunk-7.json",
    "なさ-る": "n4-details-chunk-7.json",
    "なら-ぶ": "n4-details-chunk-7.json",
    "なら-べる": "n4-details-chunk-7.json",
    "な-る": "n4-details-chunk-7.json",
    "な-れる": "n4-details-chunk-7.json",
    "にあ-う": "n4-details-chunk-7.json",
    "に-げる": "n4-details-chunk-7.json",
    "にる": "n4-details-chunk-7.json",
    "ぬ-ぐ": "n4-details-chunk-7.json",
    "ぬす-む": "n4-details-chunk-7.json",
    "ぬ-る": "n4-details-chunk-7.json",
    "ぬ-れる": "n4-details-chunk-7.json",
    "ねが-う": "n4-details-chunk-7.json",
    "ねむ-る": "n4-details-chunk-7.json",
    "のこ-る": "n4-details-chunk-7.json",
    "のりか-える": "n4-details-chunk-7.json",
    "はいけんする": "n4-details-chunk-7.json",
    "は-く": "n4-details-chunk-7.json",
    "はこ-ぶ": "n4-details-chunk-7.json",
    "はし-る": "n4-details-chunk-7.json",
    "はじ-める": "n4-details-chunk-7.json",
    "はたら-く": "n4-details-chunk-7.json",
    "はら-う": "n4-details-chunk-7.json",
    "は-る": "n4-details-chunk-7.json",
    "は-れる": "n4-details-chunk-7.json",
    "ひ-える": "n4-details-chunk-7.json",
    "ひか-る": "n4-details-chunk-7.json",
    "ひ-く": "n4-details-chunk-7.json",
    "ひっこ-す": "n4-details-chunk-7.json",
    "ひら-く": "n4-details-chunk-7.json",
    "ひろ-う": "n4-details-chunk-7.json",
    "ふ-える": "n4-details-chunk-8.json",
    "ふ-く": "n4-details-chunk-8.json",
    "ふと-る": "n4-details-chunk-8.json",
    "ふ-む": "n4-details-chunk-8.json",
    "ぶつか-る": "n4-details-chunk-8.json",
    "ほ-める": "n4-details-chunk-8.json",
    "まい-る": "n4-details-chunk-8.json",
    "ま-ける": "n4-details-chunk-8.json",
    "まちが-える": "n4-details-chunk-8.json",
    "まにあ-う": "n4-details-chunk-8.json",
    "まも-る": "n4-details-chunk-8.json",
    "まわ-る": "n4-details-chunk-8.json",
    "み-える": "n4-details-chunk-8.json",
    "みつか-る": "n4-details-chunk-8.json",
    "みつ-ける": "n4-details-chunk-8.json",
    "むか-える": "n4-details-chunk-8.json",
    "めしあが-る": "n4-details-chunk-8.json",
    "もうしあ-げる": "n4-details-chunk-8.json",
    "もう-す": "n4-details-chunk-8.json",
    "もど-す": "n4-details-chunk-8.json",
    "もど-る": "n4-details-chunk-8.json",
    "もら-う": "n4-details-chunk-8.json",
    "や-く": "n4-details-chunk-8.json",
    "や-ける": "n4-details-chunk-8.json",
    "や-せる": "n4-details-chunk-8.json",
    "や-む": "n4-details-chunk-8.json",
    "や-める": "n4-details-chunk-8.json",
    "や-る": "n4-details-chunk-8.json",
    "ゆ-く": "n4-details-chunk-8.json",
    "ゆ-れる": "n4-details-chunk-8.json",
    "よご-れる": "n4-details-chunk-8.json",
    "よ-る": "n4-details-chunk-8.json",
    "よろこ-ぶ": "n4-details-chunk-8.json",
    "わか-す": "n4-details-chunk-8.json",
    "わか-れる": "n4-details-chunk-8.json",
    "わ-く": "n4-details-chunk-8.json",
    "わす-れる": "n4-details-chunk-8.json",
    "わた-す": "n4-details-chunk-8.json",
    "わた-る": "n4-details-chunk-8.json",
    "わら-う": "n4-details-chunk-8.json",
    "わ-る": "n4-details-chunk-8.json",
    "わ-れる": "n4-details-chunk-8.json",
    "けれども": "n4-details-chunk-8.json",
    "など": "n4-details-chunk-8.json",
    "ばかり": "n4-details-chunk-8.json",
    "もの": "n4-details-chunk-8.json",
    "あさ-い": "n4-details-chunk-8.json",
    "あつ-い": "n4-details-chunk-8.json",
    "うつくし-い": "n4-details-chunk-8.json",
    "うま-い": "n4-details-chunk-8.json",
    "うれし-い": "n4-details-chunk-8.json",
    "おかし-い": "n4-details-chunk-8.json",
    "おとなし-い": "n4-details-chunk-8.json",
    "かた-い": "n4-details-chunk-8.json",
    "かっこいい": "n4-details-chunk-8.json",
    "かっこわるい": "n4-details-chunk-8.json",
    "かなし-い": "n4-details-chunk-8.json",
    "きびし-い": "n4-details-chunk-8.json",
    "くるし-い": "n4-details-chunk-8.json",
    "こまか-い": "n4-details-chunk-8.json",
    "こわ-い": "n4-details-chunk-8.json",
    "さびし-い": "n4-details-chunk-8.json",
    "しかたな-い": "n4-details-chunk-8.json",
    "したし-い": "n4-details-chunk-8.json",
    "すご-い": "n4-details-chunk-8.json",
    "すずし-い": "n4-details-chunk-8.json",
    "すばらし-い": "n4-details-chunk-8.json",
    "ただし-い": "n4-details-chunk-8.json",
    "つめた-い": "n4-details-chunk-8.json",
    "にが-い": "n4-details-chunk-8.json",
    "ぬる-い": "n4-details-chunk-8.json",
    "ねむ-い": "n4-details-chunk-8.json",
    "ねむた-い": "n4-details-chunk-8.json",
    "はずかし-い": "n4-details-chunk-8.json",
    "ひど-い": "n4-details-chunk-8.json",
    "ふか-い": "n4-details-chunk-8.json",
    "ふと-い": "n4-details-chunk-8.json",
    "ほし-い": "n4-details-chunk-8.json",
    "ほそ-い": "n4-details-chunk-8.json",
    "まる-い": "n4-details-chunk-8.json",
    "めずらし-い": "n4-details-chunk-8.json",
    "やさし-い": "n4-details-chunk-8.json",
    "やわらか-い": "n4-details-chunk-8.json",
    "よろし-い": "n4-details-chunk-8.json",
    "わか-い": "n4-details-chunk-8.json",
    "ああ": "n4-details-chunk-8.json",
    "あんなに": "n4-details-chunk-8.json",
    "いかが": "n4-details-chunk-8.json",
    "いちいち": "n4-details-chunk-8.json",
    "いったい": "n4-details-chunk-8.json",
    "いっぱい": "n4-details-chunk-8.json",
    "いつか": "n4-details-chunk-8.json",
    "かならず": "n4-details-chunk-8.json",
    "かなり": "n4-details-chunk-8.json",
    "きっと": "n4-details-chunk-8.json",
    "きゅうに": "n4-details-chunk-8.json",
    "けっこう": "n4-details-chunk-8.json",
    "けっして": "n4-details-chunk-8.json",
    "こんなに": "n4-details-chunk-8.json",
    "じゅうぶん": "n4-details-chunk-8.json",
    "すぐに": "n4-details-chunk-9.json",
    "すっかり": "n4-details-chunk-9.json",
    "ずいぶん": "n4-details-chunk-9.json",
    "ずっと": "n4-details-chunk-9.json",
    "ぜんぜん": "n4-details-chunk-9.json",
    "そう": "n4-details-chunk-9.json",
    "それほど": "n4-details-chunk-9.json",
    "そろそろ": "n4-details-chunk-9.json",
    "そんなに": "n4-details-chunk-9.json",
    "たいてい": "n4-details-chunk-9.json",
    "たしか": "n4-details-chunk-9.json",
    "たとえば": "n4-details-chunk-9.json",
    "だいぶ": "n4-details-chunk-9.json",
    "ちっとも": "n4-details-chunk-9.json",
    "ちょうど": "n4-details-chunk-9.json",
    "できるだけ": "n4-details-chunk-9.json",
    "とうとう": "n4-details-chunk-9.json",
    "とくに": "n4-details-chunk-9.json",
    "とくべつ": "n4-details-chunk-9.json",
    "どんどん": "n4-details-chunk-9.json",
    "どんなに": "n4-details-chunk-9.json",
    "なかなか": "n4-details-chunk-9.json",
    "なるべく": "n4-details-chunk-9.json",
    "なるほど": "n4-details-chunk-9.json",
    "はじめて": "n4-details-chunk-9.json",
    "はじめに": "n4-details-chunk-9.json",
    "はっきり": "n4-details-chunk-9.json",
    "ひじょうに": "n4-details-chunk-9.json",
    "ふつう": "n4-details-chunk-9.json",
    "ぺらぺら": "n4-details-chunk-9.json",
    "ほんとうに": "n4-details-chunk-9.json",
    "まず": "n4-details-chunk-9.json",
    "もう": "n4-details-chunk-9.json",
    "もうすぐ": "n4-details-chunk-9.json",
    "もうひとつ": "n4-details-chunk-9.json",
    "もし": "n4-details-chunk-9.json",
    "もちろん": "n4-details-chunk-9.json",
    "やっと": "n4-details-chunk-9.json",
    "やはり": "n4-details-chunk-9.json",
    "よく": "n4-details-chunk-9.json",
    "わざわざ": "n4-details-chunk-9.json",
    "あの": "n4-details-chunk-9.json",
    "ええ": "n4-details-chunk-9.json",
    "お": "n4-details-chunk-9.json",
    "おや": "n4-details-chunk-9.json",
    "さあ": "n4-details-chunk-9.json",
    "さかん": "n4-details-chunk-9.json",
    "たいせつ": "n4-details-chunk-9.json",
    "りっぱ": "n4-details-chunk-9.json",
    "おだいじに": "n4-details-chunk-9.json",
    "これから": "n4-details-chunk-9.json",
    "しかし": "n4-details-chunk-9.json",
    "じゃ": "n4-details-chunk-9.json",
    "すると": "n4-details-chunk-9.json",
    "そうして": "n4-details-chunk-9.json",
    "そして": "n4-details-chunk-9.json",
    "それから": "n4-details-chunk-9.json",
    "それで": "n4-details-chunk-9.json",
    "それでは": "n4-details-chunk-9.json",
    "それに": "n4-details-chunk-9.json",
    "たまに": "n4-details-chunk-9.json",
    "たりない": "n4-details-chunk-9.json",
    "だから": "n4-details-chunk-9.json",
    "つまらない": "n4-details-chunk-9.json",
    "では": "n4-details-chunk-9.json",
    "ない": "n4-details-chunk-9.json",
    "または": "n4-details-chunk-9.json"
  }
}